[
  {
    "_id": {
      "$oid": "8c6dfeb7-21e6-48c2-9db3-25ecd6d384be"
    },
    "companyName": "Ionos",
    "packageTitle": "Standard",
    "logo": "https://sm.pcmag.com/t/pcmag_uk/review/i/ionos-web-/ionos-web-hosting_pm4k.1920.jpg",
    "websiteLimit": "1 Mailbox",
    "ssdStorage": "100 GB storage",
    "mailBox": "1 Mailbox",
    "freeDomain": "Free domain & SSL certificate",
    "sslCert": "Free domain & SSL certificate",
    "hostPrice": "£6/month",
    "dealPrice": "3",
    "additions": "<ul class='additions'><li>Real-time scaling with just one click, exclusive to IONOS</li><li>Premium 24/7 support with a personal consultant</li></ul>"
  },
  {
    "_id": {
      "$oid": "bf54d451-5cd2-457f-9c9b-1722110ea6ea"
    },
    "companyName": "Ionos",
    "packageTitle": "Plus",
    "logo": "https://sm.pcmag.com/t/pcmag_uk/review/i/ionos-web-/ionos-web-hosting_pm4k.1920.jpg",
    "websiteLimit": "1 Mailbox",
    "ssdStorage": "250 GB redundant storage",
    "mailBox": "1 Mailbox",
    "freeDomain": "Free domain & SSL certificate",
    "sslCert": "Free domain & SSL certificate",
    "hostPrice": "£9/month",
    "dealPrice": "1",
    "additions": "<ul class='additions'><li>Real-time scaling with just one click, exclusive to IONOS</li><li>Premium 24/7 support with a personal consultant</li></ul>"
  },
  {
    "_id": {
      "$oid": "bced65a8-3cac-48a2-89da-800cf9227456"
    },
    "companyName": "Ionos",
    "packageTitle": "Premium",
    "logo": "https://sm.pcmag.com/t/pcmag_uk/review/i/ionos-web-/ionos-web-hosting_pm4k.1920.jpg",
    "websiteLimit": "1 Mailbox",
    "ssdStorage": "350 GB redundant storage",
    "mailBox": "1 Mailbox",
    "freeDomain": "Free domain & SSL certificate",
    "sslCert": "Free domain & SSL certificate",
    "hostPrice": "£16/month",
    "dealPrice": "8",
    "additions": "<ul class='additions'><li>Real-time scaling with just one click, exclusive to IONOS</li><li>Premium 24/7 support with a personal consultant</li></ul>"
  },
  {
    "_id": {
      "$oid": "bc8613e4-017e-4132-8b8c-94f0dd4e927e"
    },
    "companyName": "Ionos",
    "packageTitle": "Ultimate",
    "logo": "https://sm.pcmag.com/t/pcmag_uk/review/i/ionos-web-/ionos-web-hosting_pm4k.1920.jpg",
    "websiteLimit": "1 Mailbox",
    "ssdStorage": "500 GB redundant storage",
    "mailBox": "1 Mailbox",
    "freeDomain": "Free domain & SSL certificate",
    "sslCert": "Free domain & SSL certificate",
    "hostPrice": "£24/month",
    "dealPrice": "12",
    "additions": "<ul class='additions'><li>Real-time scaling with just one click, exclusive to IONOS</li><li>Premium 24/7 support with a personal consultant</li></ul>"
  },
  {
    "_id": {
      "$oid": "ee179c29-2b9a-400d-9b6a-3db8c8912586"
    },
    "companyName": "Fasthosts",
    "packageTitle": "Start",
    "logo": "https://ygo-assets-entities-emea.yougov.net/00a07d47-21f2-11e8-91d7-d17ce050fa91.jpg?ph=264",
    "websiteLimit": "1",
    "ssdStorage": "100GB",
    "mailBox": "1x",
    "freeDomain": "",
    "sslCert": "",
    "hostPrice": "£5",
    "dealPrice": "First 3 months\n£1\nper month\n\nthen £5 per month",
    "additions": ""
  },
  {
    "_id": {
      "$oid": "42012c4e-0596-4382-8f34-1eece0a89e8d"
    },
    "companyName": "Fasthosts",
    "packageTitle": "Grow",
    "logo": "https://ygo-assets-entities-emea.yougov.net/00a07d47-21f2-11e8-91d7-d17ce050fa91.jpg?ph=264",
    "websiteLimit": "3",
    "ssdStorage": "250GB",
    "mailBox": "2x",
    "freeDomain": "",
    "sslCert": "",
    "hostPrice": "£7",
    "dealPrice": "First 3 months\n£2\nper month\n\nthen £7 per month",
    "additions": ""
  },
  {
    "_id": {
      "$oid": "0b641595-2388-452a-bbc7-f5bcc9110710"
    },
    "companyName": "Fasthosts",
    "packageTitle": "Scale",
    "logo": "https://ygo-assets-entities-emea.yougov.net/00a07d47-21f2-11e8-91d7-d17ce050fa91.jpg?ph=264",
    "websiteLimit": "10",
    "ssdStorage": "350GB",
    "mailBox": "4x",
    "freeDomain": "",
    "sslCert": "",
    "hostPrice": "£12",
    "dealPrice": "First 6 months\n49p\nper month\n\nthen £12 per month",
    "additions": ""
  },
  {
    "_id": {
      "$oid": "8144c928-794a-4fc5-8d0d-2faadaf83c59"
    },
    "companyName": "Fasthosts",
    "packageTitle": "Pro",
    "logo": "https://ygo-assets-entities-emea.yougov.net/00a07d47-21f2-11e8-91d7-d17ce050fa91.jpg?ph=264",
    "websiteLimit": "100",
    "ssdStorage": "500GB",
    "mailBox": "8x",
    "freeDomain": "",
    "sslCert": "",
    "hostPrice": "£18",
    "dealPrice": "First 3 months\n£8\nper month\n\nthen £18 per month",
    "additions": ""
  }
]
