[
  {
    "_id": {
      "$oid": "bece8096-a85c-48cd-90e3-72159f959f33"
    },
    "companyName": "Ionos",
    "logo": "https://sm.pcmag.com/t/pcmag_uk/review/i/ionos-web-/ionos-web-hosting_pm4k.1920.jpg",
    "packageTitle": "Standard",
    "ssdStorage": "100 GB storage",
    "hostPrice": "£6.00/month",
    "websiteLimit": "1 Mailbox",
    "mailBox": "1 Mailbox",
    "freeDomain": "Free domain & SSL certificate",
    "sslCert": "Free domain & SSL certificate",
    "dealPrice": "",
    "greenHosting": true,
    "additions1": [
      "Real-time scaling with just one click, exclusive to IONOS"
    ],
    "additions2": [
      "Premium 24/7 support with a personal consultant"
    ]
  },
  {
    "_id": {
      "$oid": "749d0b15-6871-428b-b2f3-077d930a103f"
    },
    "companyName": "Ionos",
    "logo": "https://sm.pcmag.com/t/pcmag_uk/review/i/ionos-web-/ionos-web-hosting_pm4k.1920.jpg",
    "packageTitle": "Plus",
    "ssdStorage": "250 GB redundant storage",
    "hostPrice": "£9.00/month",
    "websiteLimit": "1 Mailbox",
    "mailBox": "1 Mailbox",
    "freeDomain": "Free domain & SSL certificate",
    "sslCert": "Free domain & SSL certificate",
    "dealPrice": "",
    "greenHosting": true,
    "additions1": [
      ""
    ],
    "additions2": [
      ""
    ]
  },
  {
    "_id": {
      "$oid": "7eceb11a-d482-4e4c-8a5b-8d2b50f67544"
    },
    "companyName": "Ionos",
    "logo": "https://sm.pcmag.com/t/pcmag_uk/review/i/ionos-web-/ionos-web-hosting_pm4k.1920.jpg",
    "packageTitle": "Premium",
    "ssdStorage": "350 GB redundant storage",
    "hostPrice": "£16.00/month",
    "websiteLimit": "1 Mailbox",
    "mailBox": "1 Mailbox",
    "freeDomain": "Free domain & SSL certificate",
    "sslCert": "Free domain & SSL certificate",
    "dealPrice": "",
    "greenHosting": true,
    "additions1": [
      ""
    ],
    "additions2": [
      ""
    ]
  },
  {
    "_id": {
      "$oid": "c6c4736f-c757-41ae-a2b4-ad07f4c1b1f9"
    },
    "companyName": "Ionos",
    "logo": "https://sm.pcmag.com/t/pcmag_uk/review/i/ionos-web-/ionos-web-hosting_pm4k.1920.jpg",
    "packageTitle": "Ultimate",
    "ssdStorage": "500 GB redundant storage",
    "hostPrice": "£24.00/month",
    "websiteLimit": "1 Mailbox",
    "mailBox": "1 Mailbox",
    "freeDomain": "Free domain & SSL certificate",
    "sslCert": "Free domain & SSL certificate",
    "dealPrice": "",
    "greenHosting": true,
    "additions1": [
      ""
    ],
    "additions2": [
      ""
    ]
  },
  {
    "_id": {
      "$oid": "cef804e5-3559-4eaa-8118-73ab0376922c"
    },
    "companyName": "Fasthosts",
    "logo": "https://ygo-assets-entities-emea.yougov.net/00a07d47-21f2-11e8-91d7-d17ce050fa91.jpg?ph=264",
    "packageTitle": "Start",
    "ssdStorage": "100GB",
    "hostPrice": "£5.00/month",
    "websiteLimit": "1",
    "mailBox": "1x",
    "freeDomain": "1x",
    "sslCert": "",
    "dealPrice": "First 3 months\n£1\nper month\n\nthen £5 per month",
    "greenHosting": false,
    "additions1": [
      "30-day money-back guarantee"
    ],
    "additions2": [
      ""
    ]
  },
  {
    "_id": {
      "$oid": "39f8e8d6-5c9d-43e2-82e4-f00731711920"
    },
    "companyName": "Fasthosts",
    "logo": "https://ygo-assets-entities-emea.yougov.net/00a07d47-21f2-11e8-91d7-d17ce050fa91.jpg?ph=264",
    "packageTitle": "Grow",
    "ssdStorage": "250GB",
    "hostPrice": "£7.00/month",
    "websiteLimit": "3",
    "mailBox": "2x",
    "freeDomain": "2x",
    "sslCert": "",
    "dealPrice": "First 3 months\n£2\nper month\n\nthen £7 per month",
    "greenHosting": false,
    "additions1": [
      ""
    ],
    "additions2": [
      ""
    ]
  },
  {
    "_id": {
      "$oid": "709cb0b6-9fbc-4e8f-b076-ad3e5b1f3179"
    },
    "companyName": "Fasthosts",
    "logo": "https://ygo-assets-entities-emea.yougov.net/00a07d47-21f2-11e8-91d7-d17ce050fa91.jpg?ph=264",
    "packageTitle": "Scale",
    "ssdStorage": "350GB",
    "hostPrice": "£12.00/month",
    "websiteLimit": "10",
    "mailBox": "4x",
    "freeDomain": "3x",
    "sslCert": "",
    "dealPrice": "First 6 months\n49p\nper month\n\nthen £12 per month",
    "greenHosting": false,
    "additions1": [
      ""
    ],
    "additions2": [
      ""
    ]
  },
  {
    "_id": {
      "$oid": "633990f3-afba-436b-86da-edb3e258294e"
    },
    "companyName": "Fasthosts",
    "logo": "https://ygo-assets-entities-emea.yougov.net/00a07d47-21f2-11e8-91d7-d17ce050fa91.jpg?ph=264",
    "packageTitle": "Pro",
    "ssdStorage": "500GB",
    "hostPrice": "£18.00/month",
    "websiteLimit": "100",
    "mailBox": "8x",
    "freeDomain": "5x",
    "sslCert": "",
    "dealPrice": "First 3 months\n£8\nper month\n\nthen £18 per month",
    "greenHosting": false,
    "additions1": [
      ""
    ],
    "additions2": [
      ""
    ]
  },
  {
    "_id": {
      "$oid": "76cbedef-cf6c-42d1-b360-93200b3becf0"
    },
    "companyName": "20i",
    "logo": "https://www.20i.com/assets/images/20i-logo.svg",
    "packageTitle": "",
    "ssdStorage": "Unlimited",
    "hostPrice": "£39.99/month",
    "websiteLimit": "50",
    "mailBox": "Unlimited",
    "freeDomain": "",
    "sslCert": "Unlimited",
    "dealPrice": "First month £1",
    "greenHosting": false,
    "additions1": [
      "Unlimited SSD webspace, bandwidth, databases, SSL & email"
    ],
    "additions2": [
      ""
    ]
  },
  {
    "_id": {
      "$oid": "6c9c9146-b7e5-4e5a-b95b-e15707137bcb"
    },
    "companyName": "20i",
    "logo": "https://www.20i.com/assets/images/20i-logo.svg",
    "packageTitle": "",
    "ssdStorage": "Unlimited",
    "hostPrice": "£69.99/month",
    "websiteLimit": "500",
    "mailBox": "Unlimited",
    "freeDomain": "",
    "sslCert": "Unlimited",
    "dealPrice": "First month £1",
    "greenHosting": false,
    "additions1": [
      ""
    ],
    "additions2": [
      ""
    ]
  },
  {
    "_id": {
      "$oid": "e86aa7c8-f0dd-4e52-926b-079d3a98f70f"
    },
    "companyName": "20i",
    "logo": "https://www.20i.com/assets/images/20i-logo.svg",
    "packageTitle": "",
    "ssdStorage": "Unlimited",
    "hostPrice": "£99.99/month",
    "websiteLimit": "Unlimited",
    "mailBox": "Unlimited",
    "freeDomain": "",
    "sslCert": "Unlimited",
    "dealPrice": "First month £1",
    "greenHosting": false,
    "additions1": [
      ""
    ],
    "additions2": [
      ""
    ]
  },
  {
    "_id": {
      "$oid": "a53d3396-9460-4374-b656-7d70d30b8d56"
    },
    "companyName": "Guru",
    "logo": "https://my.guru.co.uk/templates/gurunew/img/guru.svg",
    "packageTitle": "Reseller Account 10",
    "ssdStorage": "100GB Fast NVMe SSD Storage",
    "hostPrice": "£25.49/month",
    "websiteLimit": "10 cPanel Accounts",
    "mailBox": "Unlimited Email Accounts",
    "freeDomain": "",
    "sslCert": "Free SSL Certificates",
    "dealPrice": "",
    "greenHosting": false,
    "additions1": [
      "White Label Services"
    ],
    "additions2": [
      ""
    ]
  },
  {
    "_id": {
      "$oid": "eb78d5d1-1b66-477a-bcfa-12df91ace93c"
    },
    "companyName": "Guru",
    "logo": "https://my.guru.co.uk/templates/gurunew/img/guru.svg",
    "packageTitle": "Reseller Account 100",
    "ssdStorage": "100GB Fast NVMe SSD Storage",
    "hostPrice": "£36.99/month",
    "websiteLimit": "100 cPanel Accounts",
    "mailBox": "Unlimited Email Accounts",
    "freeDomain": "",
    "sslCert": "Free SSL Certificates",
    "dealPrice": "",
    "greenHosting": false,
    "additions1": [
      "White Label Services"
    ],
    "additions2": [
      ""
    ]
  },
  {
    "_id": {
      "$oid": "d017a7f1-f695-402b-8aab-25b8e407b008"
    },
    "companyName": "Guru",
    "logo": "https://my.guru.co.uk/templates/gurunew/img/guru.svg",
    "packageTitle": "Reseller Account 250",
    "ssdStorage": "250GB Fast NVMe SSD Storage",
    "hostPrice": "£104.99/month",
    "websiteLimit": "250 cPanel Accounts",
    "mailBox": "Unlimited Email Accounts",
    "freeDomain": "",
    "sslCert": "Free SSL Certificates",
    "dealPrice": "",
    "greenHosting": false,
    "additions1": [
      "White Label Services"
    ],
    "additions2": [
      ""
    ]
  },
  {
    "_id": {
      "$oid": "2a4ca219-beb1-4065-b83b-d079f96904fc"
    },
    "companyName": "Guru",
    "logo": "https://my.guru.co.uk/templates/gurunew/img/guru.svg",
    "packageTitle": "Reseller Account PRO 100 PRO",
    "ssdStorage": "100GB Fast NVMe SSD Storage",
    "hostPrice": "£74.99/month",
    "websiteLimit": "100 cPanel Accounts",
    "mailBox": "Unlimited Email Accounts",
    "freeDomain": "",
    "sslCert": "Free SSL Certificates",
    "dealPrice": "",
    "greenHosting": false,
    "additions1": [
      "White Label Services"
    ],
    "additions2": [
      ""
    ]
  },
  {
    "_id": {
      "$oid": "75a4ec63-7765-45b6-8490-66d8181dcb63"
    },
    "companyName": "Guru",
    "logo": "https://my.guru.co.uk/templates/gurunew/img/guru.svg",
    "packageTitle": "Reseller Account PRO 250 PRO",
    "ssdStorage": "250GB Fast NVMe SSD Storage",
    "hostPrice": "£146.99/month",
    "websiteLimit": "250 cPanel Accounts",
    "mailBox": "Unlimited Email Accounts",
    "freeDomain": "",
    "sslCert": "Free SSL Certificates",
    "dealPrice": "",
    "greenHosting": false,
    "additions1": [
      "White Label Services"
    ],
    "additions2": [
      ""
    ]
  },
  {
    "_id": {
      "$oid": "05d5c84a-7721-453a-91d7-d2b6e56e6d75"
    },
    "companyName": "OVH Cloud",
    "logo": "https://www.drupal.org/files/styles/grid-4-2x/public/OVHcloud_stacked_logo_fullcolor_RGB.png?itok=_NNzxTZa",
    "packageTitle": "Starter web hosting",
    "ssdStorage": "1 GB",
    "hostPrice": "£0.85/month",
    "websiteLimit": "1",
    "mailBox": "2 x 5GB",
    "freeDomain": "Free for the first year*",
    "sslCert": "Let’s Encrypt SSL - Free",
    "dealPrice": "",
    "greenHosting": false,
    "additions1": [
      ""
    ],
    "additions2": [
      ""
    ]
  },
  {
    "_id": {
      "$oid": "07e78f11-ce23-4f41-934c-31fa9d5f6fec"
    },
    "companyName": "OVH Cloud",
    "logo": "https://www.drupal.org/files/styles/grid-4-2x/public/OVHcloud_stacked_logo_fullcolor_RGB.png?itok=_NNzxTZa",
    "packageTitle": "Personal web hosting",
    "ssdStorage": "100 GB",
    "hostPrice": "£1.89/month",
    "websiteLimit": "5",
    "mailBox": "10 x 5GB",
    "freeDomain": "Free for the first year*",
    "sslCert": "Let’s Encrypt SSL - Free",
    "dealPrice": "",
    "greenHosting": false,
    "additions1": [
      ""
    ],
    "additions2": [
      ""
    ]
  },
  {
    "_id": {
      "$oid": "823f6989-901e-42d3-a542-1c6d7382041f"
    },
    "companyName": "OVH Cloud",
    "logo": "https://www.drupal.org/files/styles/grid-4-2x/public/OVHcloud_stacked_logo_fullcolor_RGB.png?itok=_NNzxTZa",
    "packageTitle": "Professional web hosting",
    "ssdStorage": "250 GB",
    "hostPrice": "£5.19/month",
    "websiteLimit": "10",
    "mailBox": "100 x 5GB",
    "freeDomain": "Free for the first year*",
    "sslCert": "Let’s Encrypt SSL - Free",
    "dealPrice": "",
    "greenHosting": false,
    "additions1": [
      ""
    ],
    "additions2": [
      ""
    ]
  },
  {
    "_id": {
      "$oid": "f487d6c7-7267-4bd9-937b-80fdce195a36"
    },
    "companyName": "OVH Cloud",
    "logo": "https://www.drupal.org/files/styles/grid-4-2x/public/OVHcloud_stacked_logo_fullcolor_RGB.png?itok=_NNzxTZa",
    "packageTitle": "Performance web hosting",
    "ssdStorage": "500 GB",
    "hostPrice": "£9.59/month",
    "websiteLimit": "1,000",
    "mailBox": "1,000 x 5GB",
    "freeDomain": "Free for the first year*",
    "sslCert": "Let’s Encrypt SSL - Free",
    "dealPrice": "",
    "greenHosting": false,
    "additions1": [
      ""
    ],
    "additions2": [
      ""
    ]
  }
]
