[
  {
    "_id": {
      "$oid": "39a93e703e4e44f08849bf92"
    },
    "companyName": "20i",
    "packageTitle": "Reseller 50",
    "logo": "https://www.20i.com/assets/images/20i-logo.svg",
    "websiteLimit": "50",
    "ssdStorage": "Unlimited",
    "mailBox": "Unlimited",
    "sslCert": "Unlimited",
    "hostPrice": "£39.99",
    "dealPrice": "First month £1"
  },
  {
    "_id": {
      "$oid": "ec779c9dd562714448de5803"
    },
    "companyName": "20i",
    "packageTitle": "Reseller 500",
    "logo": "https://www.20i.com/assets/images/20i-logo.svg",
    "websiteLimit": "500",
    "ssdStorage": "Unlimited",
    "mailBox": "Unlimited",
    "sslCert": "Unlimited",
    "hostPrice": "£69.99",
    "dealPrice": "First month £1"
  },
  {
    "_id": {
      "$oid": "bbb54373f17307e4c3396acb"
    },
    "companyName": "20i",
    "packageTitle": "Reseller Unlimited",
    "logo": "https://www.20i.com/assets/images/20i-logo.svg",
    "websiteLimit": "Unlimited",
    "ssdStorage": "Unlimited",
    "mailBox": "Unlimited",
    "sslCert": "Unlimited",
    "hostPrice": "£99.99",
    "dealPrice": "First month £1"
  },
  {
    "_id": {
      "$oid": "c8e2bb3e6b9572e37b9f2465"
    },
    "companyName": "Fasthosts",
    "packageTitle": "Start",
    "logo": "https://ygo-assets-entities-emea.yougov.net/00a07d47-21f2-11e8-91d7-d17ce050fa91.jpg?ph=264",
    "websiteLimit": "1",
    "ssdStorage": "100",
    "mailBox": "1",
    "sslCert": "",
    "hostPrice": "£5.00",
    "dealPrice": "First 3 months\n£1\nper month\n\nthen £5 per month"
  },
  {
    "_id": {
      "$oid": "e5984068185377d9a85b0339"
    },
    "companyName": "Fasthosts",
    "packageTitle": "Grow",
    "logo": "https://ygo-assets-entities-emea.yougov.net/00a07d47-21f2-11e8-91d7-d17ce050fa91.jpg?ph=264",
    "websiteLimit": "3",
    "ssdStorage": "250",
    "mailBox": "2",
    "sslCert": "",
    "hostPrice": "£7.00",
    "dealPrice": "First 3 months\n£2\nper month\n\nthen £7 per month"
  },
  {
    "_id": {
      "$oid": "355c30eab5180f09d3003ba0"
    },
    "companyName": "Fasthosts",
    "packageTitle": "Scale",
    "logo": "https://ygo-assets-entities-emea.yougov.net/00a07d47-21f2-11e8-91d7-d17ce050fa91.jpg?ph=264",
    "websiteLimit": "10",
    "ssdStorage": "350",
    "mailBox": "4",
    "sslCert": "",
    "hostPrice": "£12.00",
    "dealPrice": "First 6 months\n49p\nper month\n\nthen £12 per month"
  },
  {
    "_id": {
      "$oid": "5a263e83deb2201046ec9060"
    },
    "companyName": "Fasthosts",
    "packageTitle": "Pro",
    "logo": "https://ygo-assets-entities-emea.yougov.net/00a07d47-21f2-11e8-91d7-d17ce050fa91.jpg?ph=264",
    "websiteLimit": "100",
    "ssdStorage": "500",
    "mailBox": "8",
    "sslCert": "",
    "hostPrice": "£18.00",
    "dealPrice": "First 3 months\n£8\nper month\n\nthen £18 per month"
  },
  {
    "_id": {
      "$oid": "0cf0fa68682ac337b0cb214d"
    },
    "companyName": "A2 Hosting",
    "packageTitle": "Ignite",
    "logo": "https://www.a2hosting.com/wp-content/themes/a2hosting/assets/header/a2hosting-logo.webp",
    "websiteLimit": "1 Website",
    "ssdStorage": "10",
    "mailBox": "Unlimited",
    "sslCert": "Free SSL Certificate",
    "hostPrice": "$2.99",
    "dealPrice": "SAVE 76%!"
  },
  {
    "_id": {
      "$oid": "e78b410787ca82611017a246"
    },
    "companyName": "A2 Hosting",
    "packageTitle": "Accel",
    "logo": "https://www.a2hosting.com/wp-content/themes/a2hosting/assets/header/a2hosting-logo.webp",
    "websiteLimit": "Unlimited Websites",
    "ssdStorage": "Unlimited",
    "mailBox": "Unlimited",
    "sslCert": "Free SSL Certificate",
    "hostPrice": "$5.99",
    "dealPrice": "SAVE 62%!"
  },
  {
    "_id": {
      "$oid": "60864d034dd4be88f726fd2f"
    },
    "companyName": "A2 Hosting",
    "packageTitle": "Turbo Velocity",
    "logo": "https://www.a2hosting.com/wp-content/themes/a2hosting/assets/header/a2hosting-logo.webp",
    "websiteLimit": "Unlimited Websites",
    "ssdStorage": "Unlimited",
    "mailBox": "Unlimited",
    "sslCert": "Free SSL Certificate",
    "hostPrice": "$7.99",
    "dealPrice": "SAVE 68%!"
  },
  {
    "_id": {
      "$oid": "50c14df628654158519bc9b2"
    },
    "companyName": "A2 Hosting",
    "packageTitle": "Turbo Nitro",
    "logo": "https://www.a2hosting.com/wp-content/themes/a2hosting/assets/header/a2hosting-logo.webp",
    "websiteLimit": "Unlimited Websites",
    "ssdStorage": "Unlimited",
    "mailBox": "Unlimited",
    "sslCert": "Free SSL Certificate",
    "hostPrice": "$14.99",
    "dealPrice": "SAVE 50%!"
  }
]
